{
  "Type": "DamageEntity",
  "Next": {
    "Type": "Serial",
    "Interactions": [
      {
        "Type": "ApplyEffect",
        "EffectId": "Burn",
        "Entity": "Target"
      },
      {
        "Type": "ClearEntityEffect",
        "Entity": "Target",
        "EntityEffectId": "Freeze"
      },
      {
        "Type": "ClearEntityEffect",
        "Entity": "Target",
        "EntityEffectId": "Potion_Health_Lesser_Regen"
      },
      {
        "Type": "ClearEntityEffect",
        "Entity": "Target",
        "EntityEffectId": "Potion_Health_Greater_Regen"
      },
      {
        "Type": "ClearEntityEffect",
        "Entity": "Target",
        "EntityEffectId": "Potion_Stamina_Regen"
      }
    ]
  },
  "DamageEffects": {
    "Knockback": {
      "Force": -0.0025,
      "Duration": 0.1
    }
  },
  "DamageCalculator": {
    "BaseDamage": {
      "Fire": 5.5
    },
    "RandomPercentageModifier": 0.0909090909091
  }
}
